media_agent_mcp/__init__.py
media_agent_mcp/async_server.py
media_agent_mcp/async_wrapper.py
media_agent_mcp/ai_models/__init__.py
media_agent_mcp/ai_models/omni_human.py
media_agent_mcp/ai_models/openaiedit.py
media_agent_mcp/ai_models/seed16.py
media_agent_mcp/ai_models/seedance.py
media_agent_mcp/ai_models/seededit.py
media_agent_mcp/ai_models/seedream.py
media_agent_mcp/ai_models/tts.py
media_agent_mcp/audio/combiner.py
media_agent_mcp/audio/speed_controller.py
media_agent_mcp/audio/tts.py
media_agent_mcp/be/README.md
media_agent_mcp/be/__init__.py
media_agent_mcp/be/app.py
media_agent_mcp/be/pyproject.toml
media_agent_mcp/be/routes_media.py
media_agent_mcp/be/routes_omni_human.py
media_agent_mcp/be/routes_subtitles.py
media_agent_mcp/be/utils.py
media_agent_mcp/be/uv.lock
media_agent_mcp/be/__pycache__/__init__.cpython-312.pyc
media_agent_mcp/be/__pycache__/app.cpython-312.pyc
media_agent_mcp/be/__pycache__/routes_media.cpython-312.pyc
media_agent_mcp/be/__pycache__/routes_omni.cpython-312.pyc
media_agent_mcp/be/__pycache__/routes_omni_human.cpython-312.pyc
media_agent_mcp/be/__pycache__/routes_subtitles.cpython-312.pyc
media_agent_mcp/be/__pycache__/utils.cpython-312.pyc
media_agent_mcp/be/fonts/en/EduNSWACTCursive-VariableFont_wght.ttf
media_agent_mcp/be/fonts/en/MozillaText-VariableFont_wght.ttf
media_agent_mcp/be/fonts/en/Roboto_Condensed-Regular.ttf
media_agent_mcp/be/fonts/zh/MaShanZheng-Regular.ttf
media_agent_mcp/be/fonts/zh/NotoSerifSC-VariableFont_wght.ttf
media_agent_mcp/be/fonts/zh/ZCOOLXiaoWei-Regular.ttf
media_agent_mcp/install_tools/__init__.py
media_agent_mcp/install_tools/installer.py
media_agent_mcp/media_selectors/__init__.py
media_agent_mcp/media_selectors/image_selector.py
media_agent_mcp/media_selectors/video_selector.py
media_agent_mcp/storage/__init__.py
media_agent_mcp/storage/tos_client.py
media_agent_mcp/video/__init__.py
media_agent_mcp/video/omni_human.py
media_agent_mcp/video/processor.py
media_agent_mcp/video/stack.py
media_agent_mcp-2.8.0.dist-info/METADATA
media_agent_mcp-2.8.0.dist-info/WHEEL
media_agent_mcp-2.8.0.dist-info/entry_points.txt
media_agent_mcp-2.8.0.dist-info/top_level.txt
media_agent_mcp-2.8.0.dist-info/RECORD
