Metadata-Version: 2.4
Name: media-agent-mcp
Version: 2.8.0
Summary: A Model Context Protocol server for media processing with AI tools
Author-email: Media Agent Team <team@mediaagent.com>
Keywords: mcp,ai,media,video,image,processing
Classifier: Development Status :: 3 - Alpha
Classifier: Intended Audience :: Developers
Classifier: License :: OSI Approved :: MIT License
Classifier: Programming Language :: Python :: 3
Classifier: Programming Language :: Python :: 3.12
Requires-Python: >=3.12
Requires-Dist: httpx>=0.28.1
Requires-Dist: opencv-python>=4.12.0.88
Requires-Dist: pillow>=11.3.0
Requires-Dist: requests>=2.32.4
Requires-Dist: tos>=2.7.1
Requires-Dist: uvicorn>=0.32.1
Requires-Dist: numpy>=1.24.0
Requires-Dist: python-dotenv>=1.0.0
Requires-Dist: volcengine>=1.0.194
Requires-Dist: openai>=1.97.1
Requires-Dist: typing-extensions>=4.14.1
Requires-Dist: loguru>=0.7.3
Requires-Dist: imageio-ffmpeg>=0.4.0
Requires-Dist: Flask>=3.0.0
Requires-Dist: pydub>=0.25.1
Requires-Dist: gunicorn>=22.0.0
Requires-Dist: audioop-lts; python_version >= "3.13"
Requires-Dist: google-genai>=1.33.0
Requires-Dist: mcp==1.11.0
Requires-Dist: gevent>=25.8.2
